robolearn/__init__.py
robolearn_python-0.1.0.dist-info/DESCRIPTION.rst
robolearn_python-0.1.0.dist-info/METADATA
robolearn_python-0.1.0.dist-info/RECORD
robolearn_python-0.1.0.dist-info/WHEEL
robolearn_python-0.1.0.dist-info/metadata.json
robolearn_python-0.1.0.dist-info/top_level.txt
