Metadata-Version: 2.0
Name: robolearn-python
Version: 0.1.0
Summary: SDK for Robolearn
Home-page: https://github.com/NoUseFreak/robolearn-python
Author: Dries De Peuter
Author-email: dries@nousefreak.be
License: MIT
Platform: UNKNOWN
Classifier: License :: OSI Approved :: MIT License
Classifier: Operating System :: OS Independent
Classifier: Programming Language :: Python
Classifier: Programming Language :: Python :: 2.7
Requires-Dist: urllib2
